ctfatsegment2/__init__.py
ctfatsegment2/ctfat_segment.py
ctfatsegment-0.2.0.dist-info/METADATA
ctfatsegment-0.2.0.dist-info/WHEEL
ctfatsegment-0.2.0.dist-info/entry_points.txt
ctfatsegment-0.2.0.dist-info/licenses/LICENSE
ctfatsegment-0.2.0.dist-info/RECORD
