Metadata-Version: 2.4
Name: ctfatsegment
Version: 0.2.0
Summary: Process whole body CT image to segment visceral and subcutaneous fat
Project-URL: GitHub, https://github.com/Daniloper/UD_ctfatsegment
Author-email: Dániel András Szabó <szabo.daniel.andras@med.unideb.hu>
License: Copyright (c) 2025 Dániel András Szabó, Faculty of Medicine, Department of Medical Imaging, University of Debrecen
License-File: LICENSE
Requires-Python: >=3.10
Requires-Dist: nibabel>=5.2.1
Requires-Dist: numpy<2.3.0,>=1.24.4
Requires-Dist: pillow>=10.4.0
Requires-Dist: pydicom>=2.4.4
Requires-Dist: scikit-image>=0.21.0
Requires-Dist: scipy>=1.10.1
Provides-Extra: dev
Requires-Dist: check-wheel-contents; extra == 'dev'
Requires-Dist: pytest; extra == 'dev'
Requires-Dist: ruff; extra == 'dev'
Requires-Dist: twine; extra == 'dev'
